{
  "EDITOR_STATE": {
    "allProjectFiles": {
      "d774ce49-0b51-4957-8f36-15636df1f5f4": {
        "id": "d774ce49-0b51-4957-8f36-15636df1f5f4",
        "parent": null,
        "name": "ktest.js",
        "type": "JS_LAMBDA",
        "isDirectory": false,
        "children": [],
        "isRemovable": true,
        "filePath": "ktest.js",
        "cursor": {
          "lineNumber": 1,
          "column": 1
        },
        "config": {
          "runtime": "nodejs10.x",
          "handler": "handler",
          "timeout": 60,
          "memory": 128,
          "layers": []
        },
        "triggers": []
      }
    },
    "openFiles": [
      "d774ce49-0b51-4957-8f36-15636df1f5f4"
    ],
    "currentFileId": "d774ce49-0b51-4957-8f36-15636df1f5f4",
    "resources": {
      "ebResource": {
        "name": "ebResource",
        "type": "EventBridge",
        "config": {
          "selectedRegion": "us-east-1"
        }
      }
    },
    "customTemplate": {
      "dialect": null,
      "definitions": null
    },
    "envVariables": [
      {
        "lambdaId": "all",
        "varKey": "SIGMA_AWS_ACC_ID",
        "varValue": null,
        "shouldPersist": false,
        "displayOnly": false,
        "editable": false
      }
    ],
    "packageJSON": {
      "dependencies": {
        "aws-sdk": {
          "name": "aws-sdk",
          "language": "nodejs",
          "version": "2.644.0",
          "dev": true,
          "notRemovable": false
        }
      }
    }
  },
  "PROJECT_META": {
    "projectName": "ktest",
    "projectDescription": "",
    "projectVersion": "1.0.0",
    "projectRegion": "us-east-1",
    "platform": "AWS",
    "language": "nodejs",
    "platformRegions": {},
    "lastSave": 1585639931596
  },
  "VCS_STATE": {
    "provider": "GitHub",
    "repo": {
      "name": "ktest",
      "url": "https://github.com/Kumudikatest/ktest"
    }
  }
}